certbot_dns_aliyundns/__init__.py
certbot_dns_aliyundns/dns_aliyundns.py
certbot_dns_aliyundns/dns_aliyundns_test.py
certbot_dns_aliyundns-0.35.4.dev0.dist-info/LICENSE.txt
certbot_dns_aliyundns-0.35.4.dev0.dist-info/METADATA
certbot_dns_aliyundns-0.35.4.dev0.dist-info/WHEEL
certbot_dns_aliyundns-0.35.4.dev0.dist-info/entry_points.txt
certbot_dns_aliyundns-0.35.4.dev0.dist-info/top_level.txt
certbot_dns_aliyundns-0.35.4.dev0.dist-info/RECORD
